codefs/__init__.py
codefs/_core.py
codefs/gitfs/__init__.py
codefs/gitfs/opener.py
codefs/githubfs/__init__.py
codefs/githubfs/opener.py
codefs/gitlabfs/__init__.py
codefs/gitlabfs/opener.py
fs_code-0.3.2.dist-info/LICENSE
fs_code-0.3.2.dist-info/METADATA
fs_code-0.3.2.dist-info/WHEEL
fs_code-0.3.2.dist-info/entry_points.txt
fs_code-0.3.2.dist-info/RECORD
