Metadata-Version: 2.1
Name: fs-code
Version: 0.3.2
Summary: PyFilesystems for GitLab, GitHub, and Git
Home-page: https://danjou.gitlab.io/fs-code
License: MIT
Author: Max Ludwig
Author-email: mail@danjou.dev
Requires-Python: >=3.8,<4.0
Classifier: License :: OSI Approved :: MIT License
Classifier: Programming Language :: Python :: 3
Classifier: Programming Language :: Python :: 3.8
Classifier: Programming Language :: Python :: 3.9
Classifier: Programming Language :: Python :: 3.10
Classifier: Programming Language :: Python :: 3.11
Classifier: Programming Language :: Python :: 3.12
Provides-Extra: all
Provides-Extra: gitfs
Provides-Extra: githubfs
Provides-Extra: gitlabfs
Requires-Dist: PyGithub (>=2.0.0,<3.0.0) ; extra == "githubfs" or extra == "all"
Requires-Dist: dulwich (==0.21.7) ; extra == "gitfs" or extra == "all"
Requires-Dist: fs (>=2.4,<3.0)
Requires-Dist: python-gitlab (>=4.0.0,<5.0.0) ; extra == "gitlabfs" or extra == "all"
Requires-Dist: requests (>=2.31,<3.0) ; extra == "githubfs" or extra == "all"
Requires-Dist: schema (>=0.7,<0.8)
Requires-Dist: werkzeug (>=3.0.0,<4.0.0) ; extra == "gitlabfs" or extra == "githubfs" or extra == "all"
Project-URL: Documentation, https://danjou.gitlab.io/fs-code
Project-URL: Repository, https://gitlab.com/dAnjou/fs-code
